deepagents_cli/__init__.py
deepagents_cli/__main__.py
deepagents_cli/commands.py
deepagents_cli/config.py
deepagents_cli/execution.py
deepagents_cli/file_ops.py
deepagents_cli/image_utils.py
deepagents_cli/input.py
deepagents_cli/main.py
deepagents_cli/optigen_config.py
deepagents_cli/shell.py
deepagents_cli/token_utils.py
deepagents_cli/ui.py
deepagents_cli/integrations/__init__.py
deepagents_cli/integrations/daytona.py
deepagents_cli/integrations/modal.py
deepagents_cli/integrations/runloop.py
deepagents_cli/integrations/sandbox_factory.py
optigen-0.1.2.dist-info/licenses/LICENSE
react_agent/__init__.py
react_agent/context.py
react_agent/graph.py
react_agent/project_snapshot.py
react_agent/prompts.py
react_agent/storage.py
react_agent/tools.py
react_agent/types.py
optigen-0.1.2.dist-info/METADATA
optigen-0.1.2.dist-info/WHEEL
optigen-0.1.2.dist-info/entry_points.txt
optigen-0.1.2.dist-info/top_level.txt
optigen-0.1.2.dist-info/RECORD
