Metadata-Version: 2.4
Name: OptiGen
Version: 0.1.2
Summary: OptiGen is a tool for automatically generating optimization projects from natural language.
Author-email: Amir Rajabi <amir@optigen.io>
License: Apache-2.0
Project-URL: Homepage, https://github.com/OptigenIO/OptiGen-core
Project-URL: Repository, https://github.com/OptigenIO/OptiGen-core
Project-URL: Issues, https://github.com/OptigenIO/OptiGen-core/issues
Classifier: Programming Language :: Python :: 3
Classifier: Programming Language :: Python :: 3.11
Classifier: Operating System :: OS Independent
Classifier: Topic :: Scientific/Engineering :: Artificial Intelligence
Classifier: Topic :: Software Development :: Libraries :: Python Modules
Classifier: Intended Audience :: Developers
Classifier: Development Status :: 4 - Beta
Requires-Python: <4.0,>=3.11
License-File: LICENSE
Requires-Dist: langgraph>=1.0.0
Requires-Dist: langchain-openai>=0.1.22
Requires-Dist: langchain-anthropic>=0.1.23
Requires-Dist: langchain>=0.2.14
Requires-Dist: langchain-fireworks>=0.1.7
Requires-Dist: python-dotenv>=1.0.1
Requires-Dist: langchain-tavily>=0.1
Requires-Dist: deepagents>=0.3.0
Requires-Dist: rich>=14.2.0
Requires-Dist: prompt-toolkit>=3.0.52
Requires-Dist: tavily>=1.1.0
Requires-Dist: pyomo>=6.9.5
Provides-Extra: dev
Requires-Dist: mypy>=1.11.1; extra == "dev"
Requires-Dist: ruff>=0.6.1; extra == "dev"
Requires-Dist: pytest>=8.3.5; extra == "dev"
Dynamic: license-file
